graphenemodeling/__init__.py
graphenemodeling/__main__.py
graphenemodeling/overview.py
graphenemodeling/statistical_distributions.py
graphenemodeling/experiments/__init__.py
graphenemodeling/experiments/tunneling.py
graphenemodeling/experiments/photonics/Emitter.py
graphenemodeling/experiments/photonics/OscillatorModels.py
graphenemodeling/experiments/photonics/__init__.py
graphenemodeling/experiments/photonics/electrodynamics.py
graphenemodeling/experiments/photonics/limits.py
graphenemodeling/experiments/photonics/optical_models.py
graphenemodeling/graphene/__init__.py
graphenemodeling/graphene/_constants.py
graphenemodeling/graphene/base.py
graphenemodeling/graphene/bilayer.py
graphenemodeling/graphene/monolayer.py
graphenemodeling/graphene/structures.py
graphenemodeling-1.1.2.dist-info/LICENSE
graphenemodeling-1.1.2.dist-info/METADATA
graphenemodeling-1.1.2.dist-info/WHEEL
graphenemodeling-1.1.2.dist-info/top_level.txt
graphenemodeling-1.1.2.dist-info/RECORD
