Metadata-Version: 2.1
Name: graphenemodeling
Version: 1.1.2
Summary: Code for modeling graphene
Home-page: https://github.com/gholdman1/graphenemodeling.git
Author: gholdman
Author-email: gholdman@protonmail.com
License: UNKNOWN
Platform: UNKNOWN
Requires-Dist: numpy
Requires-Dist: scipy
Requires-Dist: matplotlib
